condor_csv
