Metadata-Version: 1.1
Name: condor-csv
Version: 0.1.1
Summary: Make HTCondor submit files from CSV files
Home-page: https://github.com/njvack/condor_csv
Author: Nate Vack
Author-email: njvack@wisc.edu
License: MIT
Keywords: parallel_computing high_throughput_computing science condor htcondor cluster
Platform: UNKNOWN
Classifier: Development Status :: 4 - Beta
Classifier: Intended Audience :: Science/Research
Classifier: Topic :: Software Development :: Build Tools
Classifier: License :: OSI Approved :: MIT License
Classifier: Programming Language :: Python :: 2
Classifier: Programming Language :: Python :: 2.7
Classifier: Programming Language :: Python :: 3
Classifier: Programming Language :: Python :: 3.3
Classifier: Programming Language :: Python :: 3.4
Classifier: Programming Language :: Python :: 3.5
